contur
