Metadata-Version: 2.1
Name: contur
Version: 3.0.0
Summary: Model interpretation of collider-physics measurements
Home-page: UNKNOWN
Author: The Contur Collaboration
License: GPL
Keywords: BSM UFO SLHA LHC HEP physics particle
Platform: linux
Platform: MacOS
Classifier: Development Status :: 5 - Production/Stable
Classifier: Programming Language :: Python :: 3
Classifier: Topic :: Scientific/Engineering :: Physics
Classifier: Operating System :: MacOS
Classifier: Operating System :: POSIX :: Linux
Classifier: License :: OSI Approved :: GNU General Public License (GPL)
Requires-Dist: numpy
Requires-Dist: scipy
Requires-Dist: pandas
Requires-Dist: configobj
Requires-Dist: matplotlib
Requires-Dist: tqdm
Requires-Dist: pytest
Requires-Dist: pyyaml
Requires-Dist: pyslha
Requires-Dist: click
Requires-Dist: scikit-learn
Requires-Dist: pathos
Requires-Dist: uncertainties
